Workbook

Sheet Orders
A1: order_id | B1: customer_id | C1: order_date | D1: promised_delivery_time | E1: actual_delivery_time | F1: delivery_status | G1: order_total | H1: payment_method | I1: delivery_partner_id | J1: store_id
A2: 1961864118 | B2: 30065862 | C2: 45490.357 | D2: 45490.369 | E2: 45490.366 | F2: On Time | G2: 3197.07 | H2: Cash | I2: 63230 | J2: 4771
A3: 1549769649 | B3: 9573071 | C3: 45440.551 | D3: 45440.559 | E3: 45440.56 | F3: On Time | G3: 976.55 | H3: Cash | I3: 14983 | J3: 7534
A4: 9185164487 | B4: 45477575 | C4: 45558.547 | D4: 45558.559 | E4: 45558.562 | F4: On Time | G4: 839.05 | H4: UPI | I4: 39859 | J4: 9886
A5: 9644738826 | B5: 88067569 | C5: 45254.678 | D5: 45254.69 | E5: 45254.69 | F5: On Time | G5: 440.23 | H5: Card | I5: 61497 | J5: 7917
A6: 5427684290 | B6: 83298567 | C6: 45250.208 | D6: 45250.22 | E6: 45250.221 | F6: On Time | G6: 2526.68 | H6: Cash | I6: 84315 | J6: 2741
A7: 3265154092 | B7: 43367112 | C7: 45003.687 | D7: 45003.701 | E7: 45003.7 | F7: On Time | G7: 3161.43 | H7: UPI | I7: 554 | J7: 3442
A8: 4898355547 | B8: 13284996 | C8: 45032.785 | D8: 45032.792 | E8: 45032.793 | F8: On Time | G8: 956.4 | H8: Card | I8: 14630 | J8: 1318
A9: 6568151549 | B9: 88866835 | C9: 45382.268 | D9: 45382.276 | E9: 45382.277 | F9: On Time | G9: 905.47 | H9: Cash | I9: 67714 | J9: 115
A10: 6006693867 | B10: 24496983 | C10: 45120.992 | D10: 45121.001 | E10: 45121.003 | F10: On Time | G10: 1371.17 | H10: Card | I10: 91362 | J10: 9021
A11: 374186990 | B11: 52215833 | C11: 45147.053 | D11: 45147.067 | E11: 45147.072 | F11: Slightly Delayed | G11: 1601.19 | H11: Wallet | I11: 77203 | J11: 7955
A12: 4455336265 | B12: 43431724 | C12: 45168.817 | D12: 45168.824 | E12: 45168.823 | F12: On Time | G12: 2362.33 | H12: UPI | I12: 64046 | J12: 3784
A13: 3539286337 | B13: 77559557 | C13: 45041.856 | D13: 45041.864 | E13: 45041.86 | F13: On Time | G13: 1463.8 | H13: Wallet | I13: 94899 | J13: 2463
... A5001: 2494813730 | B5001: 28663279 | C5001: 45161.503 | D5001: 45161.514 | E5001: 45161.515 | F5001: On Time | G5001: 1879.46 | H5001: Card | I5001: 32851 | J5001: 5588

Sheet Order_Items
A1: order_id | B1: product_id | C1: quantity | D1: unit_price
A2: 1961864118 | B2: 642612 | C2: 3 | D2: 517.03
A3: 1549769649 | B3: 378676 | C3: 1 | D3: 881.42
A4: 9185164487 | B4: 741341 | C4: 2 | D4: 923.84
A5: 9644738826 | B5: 561860 | C5: 1 | D5: 874.78
A6: 5427684290 | B6: 602241 | C6: 2 | D6: 976.55
A7: 3265154092 | B7: 681063 | C7: 1 | D7: 321.28
A8: 4898355547 | B8: 56589 | C8: 3 | D8: 517.77
A9: 6568151549 | B9: 500739 | C9: 2 | D9: 359.98
A10: 6006693867 | B10: 490939 | C10: 1 | D10: 80.25
A11: 374186990 | B11: 760828 | C11: 2 | D11: 563.45
A12: 4455336265 | B12: 753354 | C12: 3 | D12: 423.56
A13: 3539286337 | B13: 684939 | C13: 1 | D13: 727.95
... A5001: 2494813730 | B5001: 136533 | C5001: 1 | D5001: 826.21

Sheet Products
A1: product_id | B1: product_name | C1: category | D1: brand | E1: price | F1: mrp | G1: margin_percentage | H1: shelf_life_days | I1: min_stock_level | J1: max_stock_level
A2: 153019 | B2: Onions | C2: Fruits & Vegetables | D2: Aurora LLC | E2: 947.95 | F2: 1263.93 | G2: 25 | H2: 3 | I2: 13 | J2: 88
A3: 11422 | B3: Potatoes | C3: Fruits & Vegetables | D3: Ramaswamy-Tata | E3: 127.16 | F3: 169.55 | G3: 25 | H3: 3 | I3: 20 | J3: 65
A4: 669378 | B4: Potatoes | C4: Fruits & Vegetables | D4: Chadha and Sons | E4: 212.14 | F4: 282.85 | G4: 25 | H4: 3 | I4: 23 | J4: 70
A5: 848226 | B5: Tomatoes | C5: Fruits & Vegetables | D5: Barad and Sons | E5: 209.59 | F5: 279.45 | G5: 25 | H5: 3 | I5: 10 | J5: 51
A6: 890623 | B6: Onions | C6: Fruits & Vegetables | D6: Sangha, Nagar and Varty | E6: 354.52 | F6: 472.69 | G6: 25 | H6: 3 | I6: 27 | J6: 55
A7: 965755 | B7: Bananas | C7: Fruits & Vegetables | D7: Doshi, Sarraf and Sama | E7: 532.57 | F7: 710.09 | G7: 25 | H7: 3 | I7: 21 | J7: 91
A8: 222892 | B8: Tomatoes | C8: Fruits & Vegetables | D8: Ramakrishnan-Ghose | E8: 869.22 | F8: 1158.96 | G8: 25 | H8: 3 | I8: 28 | J8: 88
A9: 516376 | B9: Onions | C9: Fruits & Vegetables | D9: Agarwal-Dhar | E9: 877.43 | F9: 1169.91 | G9: 25 | H9: 3 | I9: 21 | J9: 71
A10: 39154 | B10: Mangoes | C10: Fruits & Vegetables | D10: Suresh, Bose and Bajwa | E10: 946.86 | F10: 1262.48 | G10: 25 | H10: 3 | I10: 21 | J10: 84
A11: 34186 | B11: Mangoes | C11: Fruits & Vegetables | D11: Mandal-Kar | E11: 925.65 | F11: 1234.2 | G11: 25 | H11: 3 | I11: 27 | J11: 74
A12: 196719 | B12: Bananas | C12: Fruits & Vegetables | D12: Yogi Group | E12: 217.5 | F12: 290 | G12: 25 | H12: 3 | I12: 15 | J12: 91
A13: 478531 | B13: Carrots | C13: Fruits & Vegetables | D13: Uppal Group | E13: 825.46 | F13: 1100.61 | G13: 25 | H13: 3 | I13: 24 | J13: 90
... A269: 114414 | B269: Vitamins | C269: Pharmacy | D269: Kara-Golla | E269: 832.06 | F269: 1040.07 | G269: 20 | H269: 365 | I269: 26 | J269: 66

Sheet Customers
A1: customer_id | B1: customer_name | C1: email | D1: phone | E1: address | F1: area | G1: pincode | H1: registration_date | I1: customer_segment | J1: total_orders | K1: avg_order_value
A2: 97475543 | B2: Niharika Nagi | C2: ektataneja@example.org | D2: 912988000000 | E2: 23, Nayar Path, Bihar Sharif-154625 | F2: Udupi | G2: 321865 | H2: 45059 | I2: Premium | J2: 13 | K2: 451.92
A3: 22077605 | B3: Megha Sachar | C3: vedant45@example.com | D3: 915123000000 | E3: 51/302, Buch Chowk Srinagar-570271 | F3: Aligarh | G3: 149394 | H3: 45461 | I3: Inactive | J3: 4 | K3: 825.48
A4: 47822591 | B4: Hema Bahri | C4: samiazaan@example.com | D4: 910034000000 | E4: 941 Anne Street, Darbhanga 186125 | F4: Begusarai | G4: 621411 | H4: 45560 | I4: Regular | J4: 17 | K4: 1969.81
A5: 79726146 | B5: Zaitra Vig | C5: ishanvi87@example.org | D5: 916264000000 | E5: 43/94, Ghosh, Alappuzha 635655 | F5: Kozhikode | G5: 826054 | H5: 45203 | I5: New | J5: 4 | K5: 220.09
A6: 57102800 | B6: Januja Verma | C6: atideshpande@example.org | D6: 917294000000 | E6: 06 Om, Ambarnath 477463 | F6: Ichalkaranji | G6: 730539 | H6: 45373 | I6: Inactive | J6: 14 | K6: 578.14
A7: 54748429 | B7: Darsh More | C7: ynayar@example.org | D7: 912582000000 | E7: 26/961 Salvi Circle, Durg 406361 | F7: Visakhapatnam | G7: 883122 | H7: 45404 | I7: New | J7: 2 | K7: 669.35
A8: 49152878 | B8: Patrick Sandhu | C8: zehaanmahajan@example.org | D8: 912413000000 | E8: 304 Tara Road, Gandhinagar-559930 | F8: Gwalior | G8: 649817 | H8: 45548 | I8: Premium | J8: 4 | K8: 973.62
A9: 16379942 | B9: Harshil Kuruvilla | C9: pathakanirudh@example.org | D9: 913807000000 | E9: 37/62, Basu Chowk Sikar 515907 | F9: Orai | G9: 332997 | H9: 45392 | I9: Inactive | J9: 15 | K9: 1370.56
A10: 11071601 | B10: Ojas Ahuja | C10: sneha11@example.com | D10: 912865000000 | E10: H.No. 99 Kade Road Ramgarh 695009 | F10: Buxar | G10: 528426 | H10: 45111 | I10: Inactive | J10: 17 | K10: 1950.54
A11: 68164013 | B11: Netra Chander | C11: hwarrior@example.org | D11: 917646000000 | E11: H.No. 94 Gupta Path, Hospet-831040 | F11: Malegaon | G11: 4515 | H11: 45106 | I11: New | J11: 1 | K11: 1061.82
A12: 80404839 | B12: Kashish Dora | C12: pushti81@example.net | D12: 912464000000 | E12: H.No. 24 Pant Street, Mathura 348430 | F12: Katni | G12: 642727 | H12: 45029 | I12: Inactive | J12: 10 | K12: 1537.35
A13: 27038630 | B13: Megha Thakkar | C13: zinalsarna@example.com | D13: 916726000000 | E13: H.No. 81 Sama Street, Danapur-137828 | F13: Fatehpur | G13: 393286 | H13: 45043 | I13: Regular | J13: 11 | K13: 1307.28
... A2501: 78738569 | B2501: Eiravati Sundaram | C2501: onkar24@example.com | D2501: 914320000000 | E2501: H.No. 791, Sur Path Bally 982559 | F2501: Dewas | G2501: 342448 | H2501: 45056 | I2501: Inactive | J2501: 4 | K2501: 376.5

Sheet Feedback
A1: feedback_id | B1: order_id | C1: customer_id | D1: rating | E1: feedback_text | F1: feedback_category | G1: sentiment | H1: feedback_date
A2: 2234710 | B2: 1961864118 | C2: 30065862 | D2: 4 | E2: It was okay, nothing special. | F2: Delivery | G2: Neutral | H2: 45490
A3: 5450964 | B3: 1549769649 | C3: 9573071 | D3: 3 | E3: The order was incorrect. | F3: App Experience | G3: Negative | H3: 45440
A4: 482108 | B4: 9185164487 | C4: 45477575 | D4: 3 | E4: It was okay, nothing special. | F4: App Experience | G4: Neutral | H4: 45558
A5: 4823104 | B5: 9644738826 | C5: 88067569 | D5: 4 | E5: The product met my expectations. | F5: App Experience | G5: Neutral | H5: 45254
A6: 3537464 | B6: 5427684290 | C6: 83298567 | D6: 3 | E6: Product was damaged during delivery. | F6: Delivery | G6: Negative | H6: 45250
A7: 4089724 | B7: 3265154092 | C7: 43367112 | D7: 2 | E7: Product was damaged during delivery. | F7: Customer Service | G7: Negative | H7: 45003
A8: 230696 | B8: 4898355547 | C8: 13284996 | D8: 4 | E8: Highly recommended! | F8: Product Quality | G8: Positive | H8: 45032
A9: 2259308 | B9: 6568151549 | C9: 88866835 | D9: 2 | E9: I had a bad experience. | F9: App Experience | G9: Negative | H9: 45382
A10: 7380970 | B10: 6006693867 | C10: 24496983 | D10: 3 | E10: Product was damaged during delivery. | F10: Delivery | G10: Negative | H10: 45121
A11: 2257242 | B11: 374186990 | C11: 52215833 | D11: 3 | E11: The product met my expectations. | F11: App Experience | G11: Neutral | H11: 45147
A12: 1837573 | B12: 4455336265 | C12: 43431724 | D12: 2 | E12: Taste was not as expected. | F12: Delivery | G12: Negative | H12: 45168
A13: 258023 | B13: 3539286337 | C13: 77559557 | D13: 3 | E13: Delivery was fine, but the product could be better. | F13: Delivery | G13: Neutral | H13: 45041
... A5001: 6578433 | B5001: 2494813730 | C5001: 28663279 | D5001: 4 | E5001: It was okay, nothing special. | F5001: Customer Service | G5001: Neutral | H5001: 45161

Sheet Monthly Sales Trend chart
A3: Row Labels | B3: Sum of order_total
A4: 2023 | B4: 5464757.6
A5: Mar | B5: 272878.96
A6: Apr | B6: 554344.77
A7: May | B7: 608213.54
A8: Jun | B8: 505227.66
A9: Jul | B9: 567639.91
A10: Aug | B10: 623472.35
A11: Sep | B11: 571117.81
A12: Oct | B12: 578369.83
A13: Nov | B13: 567783.74
A14: Dec | B14: 615709.03
A15: 2024 | B15: 5544550.9
... A27: Grand Total | B27: 11009308

Sheet Category-wise Sales Chart
A3: Row Labels | B3: Sum of order_total
A4: Baby Care | B4: 35035.22
A5: Cold Drinks & Juices | B5: 54508.73
A6: Dairy & Breakfast | B6: 65223.58
A7: Fruits & Vegetables | B7: 54510.89
A8: Grocery & Staples | B8: 58993.48
A9: Household Care | B9: 54697
A10: Instant & Frozen Food | B10: 47981.2
A11: Personal Care | B11: 49390.6
A12: Pet Care | B12: 60119.37
A13: Pharmacy | B13: 55499.18
A14: Snacks & Munchies | B14: 70474.37
A15: Grand Total | B15: 606433.62

Sheet Sheet3
A3: Row Labels | B3: Sum of order_total
A4: 0 | B4: 10402875
A5: Baby Care | B5: 35035.22
A6: Cold Drinks & Juices | B6: 54508.73
A7: Dairy & Breakfast | B7: 65223.58
A8: Fruits & Vegetables | B8: 54510.89
A9: Grocery & Staples | B9: 58993.48
A10: Household Care | B10: 54697
A11: Instant & Frozen Food | B11: 47981.2
A12: Personal Care | B12: 49390.6
A13: Pet Care | B13: 60119.37
A14: Pharmacy | B14: 55499.18
A15: Snacks & Munchies | B15: 70474.37
A16: Grand Total | B16: 11009308

Sheet Payment Method-wise Sales chart
A3: Row Labels | B3: Sum of order_total
A4: Card | B4: 2865557.5
A5: Cash | B5: 2770464
A6: UPI | B6: 2658282.7
A7: Wallet | B7: 2715004.3
A8: Grand Total | B8: 11009308

Sheet Rating-wise Customer Feedback
A3: Row Labels | B3: Count of order_id
A4: 1 | B4: 540
A5: 2 | B5: 538
A6: 3 | B6: 1398
A7: 4 | B7: 1708
A8: 5 | B8: 816
A9: Grand Total | B9: 5000

Sheet Sentiment-wise Customer Feedbac
A3: Row Labels | B3: Count of order_id
A4: Negative | B4: 1642
A5: Neutral | B5: 1738
A6: Positive | B6: 1620
A7: Grand Total | B7: 5000

Sheet Dashboard
E1: BLINKIT SALES & CUSTOMER ANALYSIS DASHBOARD
A3: Total Sales | C3: Total Orders | E3: Total Quantity Sold | G3: Average Order Value
A4: =KPI_Summary!B2 -> 11009308 | C4: =KPI_Summary!B3 -> 5000 | E4: =KPI_Summary!B4 -> 10034 | G4: =KPI_Summary!B5 -> 2201.8617
A6: On-Time Delivery % | C6: Average Rating
A7: =KPI_Summary!B6 -> 0.694 | C7: =KPI_Summary!B7 -> 3.3444

Sheet Business_Insights
A1: BLINKIT SALES & CUSTOMER ANALYSIS – BUSINESS INSIGHTS
A3: 1. Overall Sales Performance
A5: The analysis shows total sales of approximately ₹1.10 crore across 5,000 orders, indicating significant overall sales volume.
A6: 2. Category-wise Sales
A7: Snack & Munchies is the highest-selling category based on total sales.
A9: 3. Payment Method Analysis
A10: Card is the most used payment method based on total sales.
A12: 4. Customer Rating Analysis
A13: Rating 4 has the highest number of customer feedback responses, with 1,708 responses.
A15: 5. Customer Sentiment Analysis
A16: Neutral sentiment has the highest number of customer feedback responses
A18: 6. Delivery Performance
... A22: The analysis provides useful insights into sales, customer feedback, payment methods, product categories, and delivery performance. These insights can help identify sales trends and areas for improving customer experience and operational performance.

Sheet Analysis
A1: order_id | B1: order_date | C1: customer_id | D1: product_id | E1: product_name | F1: category | G1: brand | H1: quantity | I1: unit_price | J1: order_total | K1: payment_method | L1: delivery_status | M1: rating | N1: feedback_category | O1: sentiment
A2: =Orders!A2 -> 1961864118 | B2: =Orders!C2 -> 45490.357 | C2: =TEXT(Orders!B2,"0") -> 30065862 | D2: =Order_Items!B2 -> 642612 | E2: =Products!B2 -> Onions | F2: =VLOOKUP(D2,Products!$A:$D,3,FALSE) -> Pet Care | G2: =Products!D2 -> Aurora LLC | H2: =Order_Items!C2 -> 3 | I2: =Order_Items!D2 -> 517.03 | J2: =Orders!G2 -> 3197.07 | K2: =Orders!H2 -> Cash | L2: =Orders!F2 -> On Time | M2: =Feedback!D2 -> 4 | N2: =Feedback!F2 -> Delivery | O2: =Feedback!G2 -> Neutral
A3: =Orders!A3 -> 1549769649 | B3: =Orders!C3 -> 45440.551 | C3: =TEXT(Orders!B3,"0") -> 9573071 | D3: =Order_Items!B3 -> 378676 | E3: =Products!B3 -> Potatoes | F3: =Products!C3 -> Fruits & Vegetables | G3: =Products!D3 -> Ramaswamy-Tata | H3: =Order_Items!C3 -> 1 | I3: =Order_Items!D3 -> 881.42 | J3: =Orders!G3 -> 976.55 | K3: =Orders!H3 -> Cash | L3: =Orders!F3 -> On Time | M3: =Feedback!D3 -> 3 | N3: =Feedback!F3 -> App Experience | O3: =Feedback!G3 -> Negative
A4: =Orders!A4 -> 9185164487 | B4: =Orders!C4 -> 45558.547 | C4: =TEXT(Orders!B4,"0") -> 45477575 | D4: =Order_Items!B4 -> 741341 | E4: =Products!B4 -> Potatoes | F4: =Products!C4 -> Fruits & Vegetables | G4: =Products!D4 -> Chadha and Sons | H4: =Order_Items!C4 -> 2 | I4: =Order_Items!D4 -> 923.84 | J4: =Orders!G4 -> 839.05 | K4: =Orders!H4 -> UPI | L4: =Orders!F4 -> On Time | M4: =Feedback!D4 -> 3 | N4: =Feedback!F4 -> App Experience | O4: =Feedback!G4 -> Neutral
A5: =Orders!A5 -> 9644738826 | B5: =Orders!C5 -> 45254.678 | C5: =TEXT(Orders!B5,"0") -> 88067569 | D5: =Order_Items!B5 -> 561860 | E5: =Products!B5 -> Tomatoes | F5: =Products!C5 -> Fruits & Vegetables | G5: =Products!D5 -> Barad and Sons | H5: =Order_Items!C5 -> 1 | I5: =Order_Items!D5 -> 874.78 | J5: =Orders!G5 -> 440.23 | K5: =Orders!H5 -> Card | L5: =Orders!F5 -> On Time | M5: =Feedback!D5 -> 4 | N5: =Feedback!F5 -> App Experience | O5: =Feedback!G5 -> Neutral
A6: =Orders!A6 -> 5427684290 | B6: =Orders!C6 -> 45250.208 | C6: =TEXT(Orders!B6,"0") -> 83298567 | D6: =Order_Items!B6 -> 602241 | E6: =Products!B6 -> Onions | F6: =Products!C6 -> Fruits & Vegetables | G6: =Products!D6 -> Sangha, Nagar and Varty | H6: =Order_Items!C6 -> 2 | I6: =Order_Items!D6 -> 976.55 | J6: =Orders!G6 -> 2526.68 | K6: =Orders!H6 -> Cash | L6: =Orders!F6 -> On Time | M6: =Feedback!D6 -> 3 | N6: =Feedback!F6 -> Delivery | O6: =Feedback!G6 -> Negative
A7: =Orders!A7 -> 3265154092 | B7: =Orders!C7 -> 45003.687 | C7: =TEXT(Orders!B7,"0") -> 43367112 | D7: =Order_Items!B7 -> 681063 | E7: =Products!B7 -> Bananas | F7: =Products!C7 -> Fruits & Vegetables | G7: =Products!D7 -> Doshi, Sarraf and Sama | H7: =Order_Items!C7 -> 1 | I7: =Order_Items!D7 -> 321.28 | J7: =Orders!G7 -> 3161.43 | K7: =Orders!H7 -> UPI | L7: =Orders!F7 -> On Time | M7: =Feedback!D7 -> 2 | N7: =Feedback!F7 -> Customer Service | O7: =Feedback!G7 -> Negative
A8: =Orders!A8 -> 4898355547 | B8: =Orders!C8 -> 45032.785 | C8: =TEXT(Orders!B8,"0") -> 13284996 | D8: =Order_Items!B8 -> 56589 | E8: =Products!B8 -> Tomatoes | F8: =Products!C8 -> Fruits & Vegetables | G8: =Products!D8 -> Ramakrishnan-Ghose | H8: =Order_Items!C8 -> 3 | I8: =Order_Items!D8 -> 517.77 | J8: =Orders!G8 -> 956.4 | K8: =Orders!H8 -> Card | L8: =Orders!F8 -> On Time | M8: =Feedback!D8 -> 4 | N8: =Feedback!F8 -> Product Quality | O8: =Feedback!G8 -> Positive
A9: =Orders!A9 -> 6568151549 | B9: =Orders!C9 -> 45382.268 | C9: =TEXT(Orders!B9,"0") -> 88866835 | D9: =Order_Items!B9 -> 500739 | E9: =Products!B9 -> Onions | F9: =Products!C9 -> Fruits & Vegetables | G9: =Products!D9 -> Agarwal-Dhar | H9: =Order_Items!C9 -> 2 | I9: =Order_Items!D9 -> 359.98 | J9: =Orders!G9 -> 905.47 | K9: =Orders!H9 -> Cash | L9: =Orders!F9 -> On Time | M9: =Feedback!D9 -> 2 | N9: =Feedback!F9 -> App Experience | O9: =Feedback!G9 -> Negative
A10: =Orders!A10 -> 6006693867 | B10: =Orders!C10 -> 45120.992 | C10: =TEXT(Orders!B10,"0") -> 24496983 | D10: =Order_Items!B10 -> 490939 | E10: =Products!B10 -> Mangoes | F10: =Products!C10 -> Fruits & Vegetables | G10: =Products!D10 -> Suresh, Bose and Bajwa | H10: =Order_Items!C10 -> 1 | I10: =Order_Items!D10 -> 80.25 | J10: =Orders!G10 -> 1371.17 | K10: =Orders!H10 -> Card | L10: =Orders!F10 -> On Time | M10: =Feedback!D10 -> 3 | N10: =Feedback!F10 -> Delivery | O10: =Feedback!G10 -> Negative
A11: =Orders!A11 -> 374186990 | B11: =Orders!C11 -> 45147.053 | C11: =TEXT(Orders!B11,"0") -> 52215833 | D11: =Order_Items!B11 -> 760828 | E11: =Products!B11 -> Mangoes | F11: =Products!C11 -> Fruits & Vegetables | G11: =Products!D11 -> Mandal-Kar | H11: =Order_Items!C11 -> 2 | I11: =Order_Items!D11 -> 563.45 | J11: =Orders!G11 -> 1601.19 | K11: =Orders!H11 -> Wallet | L11: =Orders!F11 -> Slightly Delayed | M11: =Feedback!D11 -> 3 | N11: =Feedback!F11 -> App Experience | O11: =Feedback!G11 -> Neutral
A12: =Orders!A12 -> 4455336265 | B12: =Orders!C12 -> 45168.817 | C12: =TEXT(Orders!B12,"0") -> 43431724 | D12: =Order_Items!B12 -> 753354 | E12: =Products!B12 -> Bananas | F12: =Products!C12 -> Fruits & Vegetables | G12: =Products!D12 -> Yogi Group | H12: =Order_Items!C12 -> 3 | I12: =Order_Items!D12 -> 423.56 | J12: =Orders!G12 -> 2362.33 | K12: =Orders!H12 -> UPI | L12: =Orders!F12 -> On Time | M12: =Feedback!D12 -> 2 | N12: =Feedback!F12 -> Delivery | O12: =Feedback!G12 -> Negative | Q12: =COUNT(J2:J5001) -> 5000
A13: =Orders!A13 -> 3539286337 | B13: =Orders!C13 -> 45041.856 | C13: =TEXT(Orders!B13,"0") -> 77559557 | D13: =Order_Items!B13 -> 684939 | E13: =Products!B13 -> Carrots | F13: =Products!C13 -> Fruits & Vegetables | G13: =Products!D13 -> Uppal Group | H13: =Order_Items!C13 -> 1 | I13: =Order_Items!D13 -> 727.95 | J13: =Orders!G13 -> 1463.8 | K13: =Orders!H13 -> Wallet | L13: =Orders!F13 -> On Time | M13: =Feedback!D13 -> 3 | N13: =Feedback!F13 -> Delivery | O13: =Feedback!G13 -> Neutral
A14: =Orders!A14 -> 9171116867 | B14: =Orders!C14 -> 45221.469 | C14: =TEXT(Orders!B14,"0") -> 87107263 | D14: =Order_Items!B14 -> 500739 | E14: =Products!B14 -> Potatoes | F14: =Products!C14 -> Fruits & Vegetables | G14: =Products!D14 -> Rege Group | H14: =Order_Items!C14 -> 3 | I14: =Order_Items!D14 -> 359.98 | J14: =Orders!G14 -> 822.63 | K14: =Orders!H14 -> Card | L14: =Orders!F14 -> Slightly Delayed | M14: =Feedback!D14 -> 4 | N14: =Feedback!F14 -> Customer Service | O14: =Feedback!G14 -> Neutral
A15: =Orders!A15 -> 5504941865 | B15: =Orders!C15 -> 45319.11 | C15: =TEXT(Orders!B15,"0") -> 76512976 | D15: =Order_Items!B15 -> 540618 | E15: =Products!B15 -> Tomatoes | F15: =Products!C15 -> Fruits & Vegetables | G15: =Products!D15 -> Dugar Group | H15: =Order_Items!C15 -> 1 | I15: =Order_Items!D15 -> 317.05 | J15: =Orders!G15 -> 2287.68 | K15: =Orders!H15 -> Wallet | L15: =Orders!F15 -> Slightly Delayed | M15: =Feedback!D15 -> 5 | N15: =Feedback!F15 -> App Experience | O15: =Feedback!G15 -> Positive | Q15: =COUNTIF(L2:L5001,0) -> 0
A16: =Orders!A16 -> 5868326481 | B16: =Orders!C16 -> 45366.88 | C16: =TEXT(Orders!B16,"0") -> 37556526 | D16: =Order_Items!B16 -> 53833 | E16: =Products!B16 -> Spinach | F16: =Products!C16 -> Fruits & Vegetables | G16: =Products!D16 -> Thakur, Shah and Pingle | H16: =Order_Items!C16 -> 3 | I16: =Order_Items!D16 -> 134.69 | J16: =Orders!G16 -> 1962.35 | K16: =Orders!H16 -> Wallet | L16: =Orders!F16 -> On Time | M16: =Feedback!D16 -> 4 | N16: =Feedback!F16 -> Product Quality | O16: =Feedback!G16 -> Neutral
A17: =Orders!A17 -> 2137046916 | B17: =Orders!C17 -> 45325.368 | C17: =TEXT(Orders!B17,"0") -> 12059049 | D17: =Order_Items!B17 -> 455755 | E17: =Products!B17 -> Onions | F17: =Products!C17 -> Fruits & Vegetables | G17: =Products!D17 -> Ganesan Ltd | H17: =Order_Items!C17 -> 2 | I17: =Order_Items!D17 -> 44.09 | J17: =Orders!G17 -> 3373.96 | K17: =Orders!H17 -> UPI | L17: =Orders!F17 -> On Time | M17: =Feedback!D17 -> 4 | N17: =Feedback!F17 -> Customer Service | O17: =Feedback!G17 -> Positive | Q17: =MATCH(0,L2:L5001,0)+1 -> #N/A
A18: =Orders!A18 -> 8195544338 | B18: =Orders!C18 -> 45042.169 | C18: =TEXT(Orders!B18,"0") -> 26199489 | D18: =Order_Items!B18 -> 131937 | E18: =Products!B18 -> Potatoes | F18: =Products!C18 -> Fruits & Vegetables | G18: =Products!D18 -> Chhabra-Agrawal | H18: =Order_Items!C18 -> 1 | I18: =Order_Items!D18 -> 287.81 | J18: =Orders!G18 -> 845.71 | K18: =Orders!H18 -> Wallet | L18: =Orders!F18 -> Slightly Delayed | M18: =Feedback!D18 -> 4 | N18: =Feedback!F18 -> Delivery | O18: =Feedback!G18 -> Neutral
A19: =Orders!A19 -> 2889700050 | B19: =Orders!C19 -> 45412.682 | C19: =TEXT(Orders!B19,"0") -> 84848018 | D19: =Order_Items!B19 -> 798639 | E19: =Products!B19 -> Carrots | F19: =Products!C19 -> Fruits & Vegetables | G19: =Products!D19 -> Shankar, Nadkarni and Kumer | H19: =Order_Items!C19 -> 1 | I19: =Order_Items!D19 -> 211.25 | J19: =Orders!G19 -> 2706.54 | K19: =Orders!H19 -> Wallet | L19: =Orders!F19 -> On Time | M19: =Feedback!D19 -> 4 | N19: =Feedback!F19 -> Delivery | O19: =Feedback!G19 -> Neutral
A20: =Orders!A20 -> 65827885 | B20: =Orders!C20 -> 45134.009 | C20: =TEXT(Orders!B20,"0") -> 47577193 | D20: =Order_Items!B20 -> 324809 | E20: =Products!B20 -> Potatoes | F20: =Products!C20 -> Fruits & Vegetables | G20: =Products!D20 -> Ramakrishnan, Anand and Khare | H20: =Order_Items!C20 -> 3 | I20: =Order_Items!D20 -> 608 | J20: =Orders!G20 -> 1132.98 | K20: =Orders!H20 -> Cash | L20: =Orders!F20 -> On Time | M20: =Feedback!D20 -> 1 | N20: =Feedback!F20 -> Delivery | O20: =Feedback!G20 -> Negative
A21: =Orders!A21 -> 4656471694 | B21: =Orders!C21 -> 45269.339 | C21: =TEXT(Orders!B21,"0") -> 60728956 | D21: =Order_Items!B21 -> 679284 | E21: =Products!B21 -> Carrots | F21: =Products!C21 -> Fruits & Vegetables | G21: =Products!D21 -> Bhardwaj, Bhatia and Deshmukh | H21: =Order_Items!C21 -> 1 | I21: =Order_Items!D21 -> 877.89 | J21: =Orders!G21 -> 1525.5 | K21: =Orders!H21 -> Cash | L21: =Orders!F21 -> Slightly Delayed | M21: =Feedback!D21 -> 3 | N21: =Feedback!F21 -> Customer Service | O21: =Feedback!G21 -> Negative
A22: =Orders!A22 -> 6625178717 | B22: =Orders!C22 -> 45108.183 | C22: =TEXT(Orders!B22,"0") -> 62068277 | D22: =Order_Items!B22 -> 952168 | E22: =Products!B22 -> Onions | F22: =Products!C22 -> Fruits & Vegetables | G22: =Products!D22 -> Ratta-Sagar | H22: =Order_Items!C22 -> 3 | I22: =Order_Items!D22 -> 236.95 | J22: =Orders!G22 -> 5718.09 | K22: =Orders!H22 -> Card | L22: =Orders!F22 -> Slightly Delayed | M22: =Feedback!D22 -> 2 | N22: =Feedback!F22 -> Product Quality | O22: =Feedback!G22 -> Negative
A23: =Orders!A23 -> 7169557514 | B23: =Orders!C23 -> 45006.227 | C23: =TEXT(Orders!B23,"0") -> 84824280 | D23: =Order_Items!B23 -> 706112 | E23: =Products!B23 -> Potatoes | F23: =Products!C23 -> Fruits & Vegetables | G23: =Products!D23 -> Chandran-Dass | H23: =Order_Items!C23 -> 2 | I23: =Order_Items!D23 -> 478.79 | J23: =Orders!G23 -> 2970.9 | K23: =Orders!H23 -> Card | L23: =Orders!F23 -> Slightly Delayed | M23: =Feedback!D23 -> 2 | N23: =Feedback!F23 -> Product Quality | O23: =Feedback!G23 -> Negative
A24: =Orders!A24 -> 2268306684 | B24: =Orders!C24 -> 45440.624 | C24: =TEXT(Orders!B24,"0") -> 66742602 | D24: =Order_Items!B24 -> 812607 | E24: =Products!B24 -> Carrots | F24: =Products!C24 -> Fruits & Vegetables | G24: =Products!D24 -> Mohan Group | H24: =Order_Items!C24 -> 2 | I24: =Order_Items!D24 -> 416.65 | J24: =Orders!G24 -> 2991.57 | K24: =Orders!H24 -> Wallet | L24: =Orders!F24 -> On Time | M24: =Feedback!D24 -> 5 | N24: =Feedback!F24 -> Delivery | O24: =Feedback!G24 -> Positive
A25: =Orders!A25 -> 6905293278 | B25: =Orders!C25 -> 45459.433 | C25: =TEXT(Orders!B25,"0") -> 97259564 | D25: =Order_Items!B25 -> 799952 | E25: =Products!B25 -> Potatoes | F25: =Products!C25 -> Fruits & Vegetables | G25: =Products!D25 -> Balan, Patel and Mall | H25: =Order_Items!C25 -> 1 | I25: =Order_Items!D25 -> 922.64 | J25: =Orders!G25 -> 1404.68 | K25: =Orders!H25 -> Cash | L25: =Orders!F25 -> Significantly Delayed | M25: =Feedback!D25 -> 3 | N25: =Feedback!F25 -> Delivery | O25: =Feedback!G25 -> Neutral
A26: =Orders!A26 -> 1769493463 | B26: =Orders!C26 -> 45469.301 | C26: =TEXT(Orders!B26,"0") -> 3292927 | D26: =Order_Items!B26 -> 709916 | E26: =Products!B26 -> Onions | F26: =Products!C26 -> Fruits & Vegetables | G26: =Products!D26 -> Wali, Sood and Bala | H26: =Order_Items!C26 -> 3 | I26: =Order_Items!D26 -> 33.76 | J26: =Orders!G26 -> 2541.32 | K26: =Orders!H26 -> Wallet | L26: =Orders!F26 -> On Time | M26: =Feedback!D26 -> 2 | N26: =Feedback!F26 -> App Experience | O26: =Feedback!G26 -> Negative
A27: =Orders!A27 -> 5003387344 | B27: =Orders!C27 -> 45466.453 | C27: =TEXT(Orders!B27,"0") -> 26592009 | D27: =Order_Items!B27 -> 67197 | E27: =Products!B27 -> Bananas | F27: =Products!C27 -> Fruits & Vegetables | G27: =Products!D27 -> Wable, Randhawa and Mutti | H27: =Order_Items!C27 -> 3 | I27: =Order_Items!D27 -> 552.2 | J27: =Orders!G27 -> 2475.69 | K27: =Orders!H27 -> Wallet | L27: =Orders!F27 -> On Time | M27: =Feedback!D27 -> 4 | N27: =Feedback!F27 -> Delivery | O27: =Feedback!G27 -> Neutral
A28: =Orders!A28 -> 2064484752 | B28: =Orders!C28 -> 45419.946 | C28: =TEXT(Orders!B28,"0") -> 89995124 | D28: =Order_Items!B28 -> 937542 | E28: =Products!B28 -> Carrots | F28: =Products!C28 -> Fruits & Vegetables | G28: =Products!D28 -> Subramanian, Chaudhuri and Dora | H28: =Order_Items!C28 -> 3 | I28: =Order_Items!D28 -> 97.04 | J28: =Orders!G28 -> 1949.92 | K28: =Orders!H28 -> Wallet | L28: =Orders!F28 -> On Time | M28: =Feedback!D28 -> 3 | N28: =Feedback!F28 -> Customer Service | O28: =Feedback!G28 -> Neutral
A29: =Orders!A29 -> 964822979 | B29: =Orders!C29 -> 45486.443 | C29: =TEXT(Orders!B29,"0") -> 88520326 | D29: =Order_Items!B29 -> 455755 | E29: =Products!B29 -> Cheese | F29: =Products!C29 -> Dairy & Breakfast | G29: =Products!D29 -> Hora-Roy | H29: =Order_Items!C29 -> 2 | I29: =Order_Items!D29 -> 44.09 | J29: =Orders!G29 -> 5804.23 | K29: =Orders!H29 -> Wallet | L29: =Orders!F29 -> On Time | M29: =Feedback!D29 -> 3 | N29: =Feedback!F29 -> Product Quality | O29: =Feedback!G29 -> Negative
... A5001: =Orders!A5001 -> 2494813730 | B5001: =Orders!C5001 -> 45161.503 | C5001: =TEXT(Orders!B5001,"0") -> 28663279 | D5001: =Order_Items!B5001 -> 136533 | E5001: =Products!B5001 -> 0 | F5001: =Products!C5001 -> 0 | G5001: =Products!D5001 -> 0 | H5001: =Order_Items!C5001 -> 1 | I5001: =Order_Items!D5001 -> 826.21 | J5001: =Orders!G5001 -> 1879.46 | K5001: =Orders!H5001 -> Card | L5001: =Orders!F5001 -> On Time | M5001: =Feedback!D5001 -> 4 | N5001: =Feedback!F5001 -> Customer Service | O5001: =Feedback!G5001 -> Neutral

Sheet KPI_Summary
A1: KPI | B1: Value
A2: Total Sales | B2: =SUM(Analysis!J2:J5002) -> 11009308
A3: Total Orders | B3: =COUNTA(Analysis!A2:A5002) -> 5000
A4: Total Quantity Sold | B4: =SUM(Analysis!H2:H5001) -> 10034
A5: Average Order Value | B5: =AVERAGE(Analysis!J2:J5001) -> 2201.8617
A6: On-Time Delivery % | B6: =COUNTIF(Analysis!L2:L5001,"On Time")/COUNTA(Analysis!L2:L5001) -> 0.694
A7: Average Rating | B7: =AVERAGE(Analysis!M2:M5001) -> 3.3444
